<?xml version="1.0" encoding="UTF-8" ?>
<!DOCTYPE mapper PUBLIC "-//mybatis.org//DTD Mapper 3.0//EN" "http://mybatis.org/dtd/mybatis-3-mapper.dtd" >
<mapper namespace="com.sts.blue.app_m.mybatis_generator.dao.AccountUserMapper" >
  <resultMap id="BaseResultMap" type="com.sts.blue.app_m.mybatis_generator.entity.AccountUser" >
    <!--
      WARNING - @mbggenerated
      This element is automatically generated by MyBatis Generator, do not modify.
    -->
    <id column="user_id" property="userId" jdbcType="INTEGER" />
    <result column="user_name" property="userName" jdbcType="VARCHAR" />
    <result column="user_age" property="userAge" jdbcType="INTEGER" />
    <result column="user_sex" property="userSex" jdbcType="INTEGER" />
    <result column="user_phone" property="userPhone" jdbcType="VARCHAR" />
    <result column="user_mail" property="userMail" jdbcType="VARCHAR" />
    <result column="user_entry_time" property="userEntryTime" jdbcType="DATE" />
    <result column="user_idcard_type" property="userIdcardType" jdbcType="INTEGER" />
    <result column="user_idcard_num" property="userIdcardNum" jdbcType="VARCHAR" />
    <result column="user_industry" property="userIndustry" jdbcType="VARCHAR" />
    <result column="user_position" property="userPosition" jdbcType="VARCHAR" />
    <result column="user_head_ico" property="userHeadIco" jdbcType="VARCHAR" />
    <result column="user_role" property="userRole" jdbcType="INTEGER" />
    <result column="user_remark" property="userRemark" jdbcType="VARCHAR" />
  </resultMap>
  <sql id="Base_Column_List" >
    <!--
      WARNING - @mbggenerated
      This element is automatically generated by MyBatis Generator, do not modify.
    -->
    user_id, user_name, user_age, user_sex, user_phone, user_mail, user_entry_time, user_idcard_type, 
    user_idcard_num, user_industry, user_position, user_head_ico, user_role, user_remark
  </sql>

  <sql id="UserID" >
    user_id
  </sql>

  <select id="selectByPrimaryKey" resultMap="BaseResultMap" parameterType="java.lang.Integer" >
    <!--
      WARNING - @mbggenerated
      This element is automatically generated by MyBatis Generator, do not modify.
    -->
    select 
    <include refid="Base_Column_List" />
    from account_user
    where user_id = #{userId,jdbcType=INTEGER}
  </select>

  <select id="FindUserByPhoneAndEmail" resultType="BaseResultMap" parameterType="java.lang.String" >
    <!--
      WARNING - @mbggenerated
      This element is automatically generated by MyBatis Generator, do not modify.
    -->
    select
    <include refid="Base_Column_List" />
    from account_user
    where user_phone = #{accountName,jdbcType=VARCHAR} OR user_mail = #{accountName,jdbcType=VARCHAR}
  </select>

  <delete id="deleteByPrimaryKey" parameterType="java.lang.Integer" >
    <!--
      WARNING - @mbggenerated
      This element is automatically generated by MyBatis Generator, do not modify.
    -->
    delete from account_user
    where user_id = #{userId,jdbcType=INTEGER}
  </delete>
  <insert id="insert" parameterType="com.sts.blue.app_m.mybatis_generator.entity.AccountUser" >
    <!--
      WARNING - @mbggenerated
      This element is automatically generated by MyBatis Generator, do not modify.
    -->
    insert into account_user (user_id, user_name, user_age, 
      user_sex, user_phone, user_mail, 
      user_entry_time, user_idcard_type, user_idcard_num, 
      user_industry, user_position, user_head_ico, 
      user_role, user_remark)
    values (#{userId,jdbcType=INTEGER}, #{userName,jdbcType=VARCHAR}, #{userAge,jdbcType=INTEGER}, 
      #{userSex,jdbcType=INTEGER}, #{userPhone,jdbcType=VARCHAR}, #{userMail,jdbcType=VARCHAR}, 
      #{userEntryTime,jdbcType=DATE}, #{userIdcardType,jdbcType=INTEGER}, #{userIdcardNum,jdbcType=VARCHAR}, 
      #{userIndustry,jdbcType=VARCHAR}, #{userPosition,jdbcType=VARCHAR}, #{userHeadIco,jdbcType=VARCHAR}, 
      #{userRole,jdbcType=INTEGER}, #{userRemark,jdbcType=VARCHAR})
  </insert>
  <insert id="insertSelective" parameterType="com.sts.blue.app_m.mybatis_generator.entity.AccountUser" >
    <!--
      WARNING - @mbggenerated
      This element is automatically generated by MyBatis Generator, do not modify.
    -->
    insert into account_user
    <trim prefix="(" suffix=")" suffixOverrides="," >
      <if test="userId != null" >
        user_id,
      </if>
      <if test="userName != null" >
        user_name,
      </if>
      <if test="userAge != null" >
        user_age,
      </if>
      <if test="userSex != null" >
        user_sex,
      </if>
      <if test="userPhone != null" >
        user_phone,
      </if>
      <if test="userMail != null" >
        user_mail,
      </if>
      <if test="userEntryTime != null" >
        user_entry_time,
      </if>
      <if test="userIdcardType != null" >
        user_idcard_type,
      </if>
      <if test="userIdcardNum != null" >
        user_idcard_num,
      </if>
      <if test="userIndustry != null" >
        user_industry,
      </if>
      <if test="userPosition != null" >
        user_position,
      </if>
      <if test="userHeadIco != null" >
        user_head_ico,
      </if>
      <if test="userRole != null" >
        user_role,
      </if>
      <if test="userRemark != null" >
        user_remark,
      </if>
    </trim>
    <trim prefix="values (" suffix=")" suffixOverrides="," >
      <if test="userId != null" >
        #{userId,jdbcType=INTEGER},
      </if>
      <if test="userName != null" >
        #{userName,jdbcType=VARCHAR},
      </if>
      <if test="userAge != null" >
        #{userAge,jdbcType=INTEGER},
      </if>
      <if test="userSex != null" >
        #{userSex,jdbcType=INTEGER},
      </if>
      <if test="userPhone != null" >
        #{userPhone,jdbcType=VARCHAR},
      </if>
      <if test="userMail != null" >
        #{userMail,jdbcType=VARCHAR},
      </if>
      <if test="userEntryTime != null" >
        #{userEntryTime,jdbcType=DATE},
      </if>
      <if test="userIdcardType != null" >
        #{userIdcardType,jdbcType=INTEGER},
      </if>
      <if test="userIdcardNum != null" >
        #{userIdcardNum,jdbcType=VARCHAR},
      </if>
      <if test="userIndustry != null" >
        #{userIndustry,jdbcType=VARCHAR},
      </if>
      <if test="userPosition != null" >
        #{userPosition,jdbcType=VARCHAR},
      </if>
      <if test="userHeadIco != null" >
        #{userHeadIco,jdbcType=VARCHAR},
      </if>
      <if test="userRole != null" >
        #{userRole,jdbcType=INTEGER},
      </if>
      <if test="userRemark != null" >
        #{userRemark,jdbcType=VARCHAR},
      </if>
    </trim>
  </insert>
  <update id="updateByPrimaryKeySelective" parameterType="com.sts.blue.app_m.mybatis_generator.entity.AccountUser" >
    <!--
      WARNING - @mbggenerated
      This element is automatically generated by MyBatis Generator, do not modify.
    -->
    update account_user
    <set >
      <if test="userName != null" >
        user_name = #{userName,jdbcType=VARCHAR},
      </if>
      <if test="userAge != null" >
        user_age = #{userAge,jdbcType=INTEGER},
      </if>
      <if test="userSex != null" >
        user_sex = #{userSex,jdbcType=INTEGER},
      </if>
      <if test="userPhone != null" >
        user_phone = #{userPhone,jdbcType=VARCHAR},
      </if>
      <if test="userMail != null" >
        user_mail = #{userMail,jdbcType=VARCHAR},
      </if>
      <if test="userEntryTime != null" >
        user_entry_time = #{userEntryTime,jdbcType=DATE},
      </if>
      <if test="userIdcardType != null" >
        user_idcard_type = #{userIdcardType,jdbcType=INTEGER},
      </if>
      <if test="userIdcardNum != null" >
        user_idcard_num = #{userIdcardNum,jdbcType=VARCHAR},
      </if>
      <if test="userIndustry != null" >
        user_industry = #{userIndustry,jdbcType=VARCHAR},
      </if>
      <if test="userPosition != null" >
        user_position = #{userPosition,jdbcType=VARCHAR},
      </if>
      <if test="userHeadIco != null" >
        user_head_ico = #{userHeadIco,jdbcType=VARCHAR},
      </if>
      <if test="userRole != null" >
        user_role = #{userRole,jdbcType=INTEGER},
      </if>
      <if test="userRemark != null" >
        user_remark = #{userRemark,jdbcType=VARCHAR},
      </if>
    </set>
    where user_id = #{userId,jdbcType=INTEGER}
  </update>
  <update id="updateByPrimaryKey" parameterType="com.sts.blue.app_m.mybatis_generator.entity.AccountUser" >
    <!--
      WARNING - @mbggenerated
      This element is automatically generated by MyBatis Generator, do not modify.
    -->
    update account_user
    set user_name = #{userName,jdbcType=VARCHAR},
      user_age = #{userAge,jdbcType=INTEGER},
      user_sex = #{userSex,jdbcType=INTEGER},
      user_phone = #{userPhone,jdbcType=VARCHAR},
      user_mail = #{userMail,jdbcType=VARCHAR},
      user_entry_time = #{userEntryTime,jdbcType=DATE},
      user_idcard_type = #{userIdcardType,jdbcType=INTEGER},
      user_idcard_num = #{userIdcardNum,jdbcType=VARCHAR},
      user_industry = #{userIndustry,jdbcType=VARCHAR},
      user_position = #{userPosition,jdbcType=VARCHAR},
      user_head_ico = #{userHeadIco,jdbcType=VARCHAR},
      user_role = #{userRole,jdbcType=INTEGER},
      user_remark = #{userRemark,jdbcType=VARCHAR}
    where user_id = #{userId,jdbcType=INTEGER}
  </update>

</mapper>